pixltsnorm/__init__.py
pixltsnorm/dataframe_harmonize.py
pixltsnorm/harmonize.py
pixltsnorm/models.py
pixltsnorm/utils.py
pixltsnorm/earth_engine/__init__.py
pixltsnorm/earth_engine/landsat.py
pixltsnorm-0.1.0.dist-info/LICENSE
pixltsnorm-0.1.0.dist-info/METADATA
pixltsnorm-0.1.0.dist-info/WHEEL
pixltsnorm-0.1.0.dist-info/top_level.txt
pixltsnorm-0.1.0.dist-info/RECORD
