Metadata-Version: 2.2
Name: pixltsnorm
Version: 0.1.0
Summary: Pixel-based Linear Time Series Normalizer
Author-email: Joseph Emile Honour Percival <ipercival@gmail.com>
License: MIT
Project-URL: Bug Tracker, https://github.com/iosefa/pixltsnorm
Project-URL: Source, https://github.com/iosefa/pixltsnorm
Keywords: remote sensing,time series,normalization
Classifier: Development Status :: 3 - Alpha
Classifier: Programming Language :: Python :: 3
Classifier: License :: OSI Approved :: MIT License
Classifier: Topic :: Scientific/Engineering :: GIS
Requires-Python: >=3.10
License-File: LICENSE
Requires-Dist: numpy
Requires-Dist: pandas
Requires-Dist: scikit-learn
Requires-Dist: statsmodels
Provides-Extra: earth-engine
Requires-Dist: earthengine-api>=0.1.350; extra == "earth-engine"
Provides-Extra: dev
Requires-Dist: pytest==8.0.0; extra == "dev"
Requires-Dist: jupyter~=1.0.0; extra == "dev"
Requires-Dist: pre-commit~=3.6.0; extra == "dev"
Provides-Extra: docs
Requires-Dist: mkdocs>=1.4.0; extra == "docs"
Requires-Dist: mkdocs-material>=9.0.0; extra == "docs"
Requires-Dist: mkdocs-jupyter>=0.24.0; extra == "docs"
Requires-Dist: mkdocstrings>=0.21.0; extra == "docs"
Requires-Dist: mkdocstrings-python>=0.10.0; extra == "docs"
Requires-Dist: mkdocs-git-revision-date-plugin>=0.3.2; extra == "docs"
Requires-Dist: pymdown-extensions>=9.10; extra == "docs"
